snakemake_storage_plugin_cached_http/__init__.py
snakemake_storage_plugin_cached_http/cache.py
snakemake_storage_plugin_cached_http/monkeypatch.py
snakemake_storage_plugin_cached_http-0.2.1.dist-info/METADATA
snakemake_storage_plugin_cached_http-0.2.1.dist-info/WHEEL
snakemake_storage_plugin_cached_http-0.2.1.dist-info/entry_points.txt
snakemake_storage_plugin_cached_http-0.2.1.dist-info/top_level.txt
snakemake_storage_plugin_cached_http-0.2.1.dist-info/RECORD
