Metadata-Version: 2.4
Name: snakemake-storage-plugin-cached-http
Version: 0.2.1
Summary: Snakemake storage plugin for downloading files via HTTP with caching and rate limiting
Author-email: PyPSA-Eur Authors <jonas.hoersch@openenergytransition.org>
License-Expression: MIT
Project-URL: homepage, https://github.com/pypsa/pypsa-eur
Project-URL: repository, https://github.com/pypsa/pypsa-eur
Keywords: snakemake,plugin,storage,http,cache
Classifier: Development Status :: 4 - Beta
Classifier: Intended Audience :: Science/Research
Classifier: Programming Language :: Python :: 3
Classifier: Programming Language :: Python :: 3.11
Classifier: Programming Language :: Python :: 3.12
Classifier: Programming Language :: Python :: 3.13
Requires-Python: >=3.11
Requires-Dist: httpx~=0.27
Requires-Dist: platformdirs~=4.0
Requires-Dist: reretry~=0.11
Requires-Dist: snakemake-interface-common~=1.14
Requires-Dist: snakemake-interface-storage-plugins<5.0,>=4.2
Requires-Dist: snakemake-storage-plugin-http~=0.3
Requires-Dist: tqdm-loggable~=0.2
Requires-Dist: typing-extensions~=4.15
Requires-Dist: zstandard~=0.25.0
Provides-Extra: dev
Requires-Dist: pytest>=7.0; extra == "dev"
Requires-Dist: pytest-asyncio>=0.21; extra == "dev"
